gtm_wizard/__init__.py
gtm_wizard/py.typed
gtm_wizard/server.py
gtm_wizard/resources/GTM_KNOWLEDGE_TAXONOMY.md
gtm_wizard/resources/foundations/README.md
gtm_wizard/resources/foundations/context-factors.md
gtm_wizard/resources/foundations/gtm-archetypes.md
gtm_wizard/resources/foundations/principles-not-recipes.md
gtm_wizard/resources/foundations/what-is-gtm-engineering.md
gtm_wizard/tools/__init__.py
gtm_wizard/tools/qualification.py
gtm_wizard-0.2.1.dist-info/METADATA
gtm_wizard-0.2.1.dist-info/WHEEL
gtm_wizard-0.2.1.dist-info/entry_points.txt
gtm_wizard-0.2.1.dist-info/licenses/LICENSE
gtm_wizard-0.2.1.dist-info/RECORD
