Metadata-Version: 2.4
Name: gtm-wizard
Version: 0.2.1
Summary: MCP server packaging Go-To-Market Engineering expertise for AI agents
Project-URL: Homepage, https://github.com/MathewJoseph1993/gtm-wizard
Project-URL: Repository, https://github.com/MathewJoseph1993/gtm-wizard
Project-URL: Documentation, https://github.com/MathewJoseph1993/gtm-wizard#readme
Project-URL: Issues, https://github.com/MathewJoseph1993/gtm-wizard/issues
Author-email: Mathew Joseph <mathewjoseph1993@gmail.com>
License-Expression: MIT
License-File: LICENSE
Keywords: ai-agents,go-to-market,gtm,lead-qualification,mcp,model-context-protocol,sales-automation
Classifier: Development Status :: 3 - Alpha
Classifier: Environment :: Console
Classifier: Intended Audience :: Developers
Classifier: License :: OSI Approved :: MIT License
Classifier: Programming Language :: Python :: 3
Classifier: Programming Language :: Python :: 3.10
Classifier: Programming Language :: Python :: 3.11
Classifier: Programming Language :: Python :: 3.12
Classifier: Topic :: Software Development :: Libraries :: Python Modules
Classifier: Typing :: Typed
Requires-Python: >=3.10
Requires-Dist: httpx<1.0.0,>=0.24.0
Requires-Dist: mcp<2.0.0,>=1.0.0
Requires-Dist: pydantic<3.0.0,>=2.0.0
Provides-Extra: dev
Requires-Dist: build<2.0.0,>=1.0.0; extra == 'dev'
Requires-Dist: mypy<2.0.0,>=1.0.0; extra == 'dev'
Requires-Dist: pytest-asyncio<2.0.0,>=0.21.0; extra == 'dev'
Requires-Dist: pytest-cov<8.0.0,>=4.0.0; extra == 'dev'
Requires-Dist: pytest<10.0.0,>=7.0.0; extra == 'dev'
Requires-Dist: ruff>=0.1.0; extra == 'dev'
Requires-Dist: twine<7.0.0,>=4.0.0; extra == 'dev'
